Workbook

Sheet Profit_and_Loss_2025
A1: Les Cadeaux
A2: Profit and Loss Statement | B2: FY2025 (USD)
A3: Net Sales | B3: 1850000
A4: Cost of Goods Sold (COGS) | B4: 1035000
A5: Gross Profit | B5: =B3-B4 -> 815000
A6: Operating Expenses
A7: Payroll & Benefits | B7: 360000
A8: Rent | B8: 165000
A9: Marketing | B9: 55000
A10: Packaging & Supplies | B10: 48000
A11: Shipping & Delivery Fees | B11: 42000
A12: Returns & Refunds (contra revenue) | B12: 38000
A13: Payment Processing Fees | B13: 27000
A14: Utilities | B14: 18000
A15: Software & Subscriptions | B15: 14000
A16: Repairs & Maintenance | B16: 9000
A17: Total Operating Expenses | B17: =SUM(B7:B16) -> 776000
A18: Operating Income | B18: =B5-B17 -> 39000
A19: Other Income / (Expense)
A20: Interest Expense | B20: 0
A21: Net Income | B21: =B18-B20 -> 39000

Sheet Balance_Sheet_2025
A1: Les Cadeaux
A2: Balance Sheet | B2: Dec 31, 2025 (USD)
A3: Assets
A4: Current Assets
A5: Cash | B5: 145000
A6: Accounts Receivable | B6: 18000
A7: Inventory | B7: 210000
A8: Prepaid Expenses | B8: 12000
A9: Total Current Assets | B9: =SUM(B5:B8) -> 385000
A10: Non-Current Assets
A11: Leasehold Improvements (net) | B11: 240000
A12: Furniture, Fixtures & Equipment (net) | B12: 95000
A13: Total Non-Current Assets | B13: =SUM(B11:B12) -> 335000
A14: Total Assets | B14: =B9+B13 -> 720000
A16: Liabilities
A17: Current Liabilities
A18: Accounts Payable | B18: 62000
A19: Accrued Expenses | B19: 28000
A20: Sales Tax Payable | B20: 6000
A21: Total Current Liabilities | B21: =SUM(B18:B20) -> 96000
A22: Long-Term Liabilities (Interest-Free)
A23: Owner Loan (0% interest) | B23: 70000
A24: Total Long-Term Liabilities | B24: 70000
A25: Total Liabilities | B25: =B21+B24 -> 166000
A27: Equity
A28: Owner Capital | B28: 515000
A29: Retained Earnings | B29: 39000
A30: Total Equity | B30: =B28+B29 -> 554000
A31: Total Liabilities & Equity | B31: =B25+B30 -> 720000

Sheet Competitor
A1: Ratio | B1: Competitor (Smile Gifts) | C1: Les Cadeaux (FY2025) | D1: notes
A2: Gross Margin | B2: 0.45 | C2: =_xlfn.XLOOKUP("Gross Profit",Profit_and_Loss_2025!A:A,Profit_and_Loss_2025!B:B)/_xlfn.XLOOKUP("Net Sales",Profit_and_Loss_2025!A:A,Profit_and_Loss_2025!B:B) -> 0.44054054 | D2: =_xlfn.LET(_xlpm.r,RatioTable[[#This Row],[Ratio]],_xlpm.lc,RatioTable[[#This Row],[Les Cadeaux (FY2025)]],_xlpm.sg,RatioTable[[#This Row],[Competitor (Smile Gifts)]],_xlpm.diff,_xlpm.lc-_xlpm.sg,_xlpm.isPct,NOT(OR(_xlpm.r="Current Ratio",_xlpm.r="Inventory Turnover")),_xlpm.fmt,IF(_xlpm.isPct,"0.00%","0.00"),_xlpm.dir,IF(_xlpm.diff>=0,"higher","lower"),"Les Cadeaux is "&_xlpm.dir&" than Smile Gifts by "&TEXT(ABS(_xlpm.diff),_xlpm.fmt)) -> Les Cadeaux is lower than Smile Gifts by 0.95%
A3: Operating Margin | B3: 0.04 | C3: =_xlfn.XLOOKUP("Operating Income",Profit_and_Loss_2025!A:A,Profit_and_Loss_2025!B:B)/_xlfn.XLOOKUP("Net Sales",Profit_and_Loss_2025!A:A,Profit_and_Loss_2025!B:B) -> 0.021081081 | D3: =_xlfn.LET(_xlpm.r,RatioTable[[#This Row],[Ratio]],_xlpm.lc,RatioTable[[#This Row],[Les Cadeaux (FY2025)]],_xlpm.sg,RatioTable[[#This Row],[Competitor (Smile Gifts)]],_xlpm.diff,_xlpm.lc-_xlpm.sg,_xlpm.isPct,NOT(OR(_xlpm.r="Current Ratio",_xlpm.r="Inventory Turnover")),_xlpm.fmt,IF(_xlpm.isPct,"0.00%","0.00"),_xlpm.dir,IF(_xlpm.diff>=0,"higher","lower"),"Les Cadeaux is "&_xlpm.dir&" than Smile Gifts by "&TEXT(ABS(_xlpm.diff),_xlpm.fmt)) -> Les Cadeaux is lower than Smile Gifts by 1.89%
A4: Net Margin | B4: 0.03 | C4: =_xlfn.XLOOKUP("Net Income",Profit_and_Loss_2025!A:A,Profit_and_Loss_2025!B:B)/_xlfn.XLOOKUP("Net Sales",Profit_and_Loss_2025!A:A,Profit_and_Loss_2025!B:B) -> 0.021081081 | D4: =_xlfn.LET(_xlpm.r,RatioTable[[#This Row],[Ratio]],_xlpm.lc,RatioTable[[#This Row],[Les Cadeaux (FY2025)]],_xlpm.sg,RatioTable[[#This Row],[Competitor (Smile Gifts)]],_xlpm.diff,_xlpm.lc-_xlpm.sg,_xlpm.isPct,NOT(OR(_xlpm.r="Current Ratio",_xlpm.r="Inventory Turnover")),_xlpm.fmt,IF(_xlpm.isPct,"0.00%","0.00"),_xlpm.dir,IF(_xlpm.diff>=0,"higher","lower"),"Les Cadeaux is "&_xlpm.dir&" than Smile Gifts by "&TEXT(ABS(_xlpm.diff),_xlpm.fmt)) -> Les Cadeaux is lower than Smile Gifts by 0.89%
A5: Current Ratio | B5: 3.2 | C5: =_xlfn.XLOOKUP("Total Current Assets",Balance_Sheet_2025!A:A,Balance_Sheet_2025!B:B)/_xlfn.XLOOKUP("Total Current Liabilities",Balance_Sheet_2025!A:A,Balance_Sheet_2025!B:B) -> 4.0104167 | D5: =_xlfn.LET(_xlpm.r,RatioTable[[#This Row],[Ratio]],_xlpm.lc,RatioTable[[#This Row],[Les Cadeaux (FY2025)]],_xlpm.sg,RatioTable[[#This Row],[Competitor (Smile Gifts)]],_xlpm.diff,_xlpm.lc-_xlpm.sg,_xlpm.isPct,NOT(OR(_xlpm.r="Current Ratio",_xlpm.r="Inventory Turnover")),_xlpm.fmt,IF(_xlpm.isPct,"0.00%","0.00"),_xlpm.dir,IF(_xlpm.diff>=0,"higher","lower"),"Les Cadeaux is "&_xlpm.dir&" than Smile Gifts by "&TEXT(ABS(_xlpm.diff),_xlpm.fmt)) -> Les Cadeaux is higher than Smile Gifts by 0.81
A6: Inventory Turnover | B6: 6.8 | C6: =ABS(_xlfn.XLOOKUP("Cost of Goods Sold (COGS)",Profit_and_Loss_2025!A:A,Profit_and_Loss_2025!B:B))/_xlfn.XLOOKUP("*Inventory*",Balance_Sheet_2025!A:A,Balance_Sheet_2025!B:B,,2) -> 4.9285714 | D6: =_xlfn.LET(_xlpm.r,RatioTable[[#This Row],[Ratio]],_xlpm.lc,RatioTable[[#This Row],[Les Cadeaux (FY2025)]],_xlpm.sg,RatioTable[[#This Row],[Competitor (Smile Gifts)]],_xlpm.diff,_xlpm.lc-_xlpm.sg,_xlpm.isPct,NOT(OR(_xlpm.r="Current Ratio",_xlpm.r="Inventory Turnover")),_xlpm.fmt,IF(_xlpm.isPct,"0.00%","0.00"),_xlpm.dir,IF(_xlpm.diff>=0,"higher","lower"),"Les Cadeaux is "&_xlpm.dir&" than Smile Gifts by "&TEXT(ABS(_xlpm.diff),_xlpm.fmt)) -> Les Cadeaux is lower than Smile Gifts by 1.87
