Workbook

Sheet GL
A1: Txn_ID | B1: Date | C1: Month | D1: City | E1: Region | F1: GL_Account | G1: GL_Category | H1: Memo | I1: Debit | J1: Credit | K1: Amount | L1: DC
A2: 202512-0077 | B2: 45992 | C2: 2025-12 | D2: Boston, MA | E2: New England | F2: COGS - Milk & Dairy | G2: Cost of Goods Sold | H2: Fresh milk restock | I2: 710.97 | J2: 0 | K2: 710.97 | L2: D
A3: 202512-0042 | B3: 45993 | C3: 2025-12 | D3: Boston, MA | E3: New England | F3: Sales Revenue - Cappuccino | G3: Revenue | H3: Daily POS sales batch - Cappuccino (250 cups @ $3.50) | I3: 0 | J3: 875 | K3: 875 | L3: C
A4: 202512-0069 | B4: 45993 | C4: 2025-12 | D4: Portland, ME | E4: New England | F4: Marketing & Promotions | G4: Operating | H4: Flyers & promo printing | I4: 383.43 | J4: 0 | K4: 383.43 | L4: D
A5: 202512-0073 | B5: 45993 | C5: 2025-12 | D5: Pittsburgh, PA | E5: Mid Atlantic | F5: POS / Software Subscriptions | G5: Operating | H5: Cloud POS monthly fee | I5: 188.77 | J5: 0 | K5: 188.77 | L5: D
A6: 202512-0092 | B6: 45993 | C6: 2025-12 | D6: Boston, MA | E6: New England | F6: Bank & Card Processing Fees | G6: Operating | H6: Merchant service fees | I6: 364.05 | J6: 0 | K6: 364.05 | L6: D
A7: 202512-0013 | B7: 45994 | C7: 2025-12 | D7: Buffalo, NY | E7: Mid Atlantic | F7: Sales Revenue - Mocha | G7: Revenue | H7: Daily POS sales batch - Mocha (254 cups @ $3.45) | I7: 0 | J7: 876.3 | K7: 876.3 | L7: C
A8: 202512-0016 | B8: 45994 | C8: 2025-12 | D8: New York, NY | E8: Mid Atlantic | F8: Sales Revenue - Espresso | G8: Revenue | H8: Daily POS sales batch - Espresso (206 cups @ $3.25) | I8: 0 | J8: 669.5 | K8: 669.5 | L8: C
A9: 202512-0051 | B9: 45994 | C9: 2025-12 | D9: New York, NY | E9: Mid Atlantic | F9: Sales Revenue - Cappuccino | G9: Revenue | H9: Daily POS sales batch - Cappuccino (259 cups @ $3.50) | I9: 0 | J9: 906.5 | K9: 906.5 | L9: C
A10: 202512-0052 | B10: 45994 | C10: 2025-12 | D10: Newark, NJ | E10: Mid Atlantic | F10: Sales Revenue - Cappuccino | G10: Revenue | H10: Daily POS sales batch - Cappuccino (216 cups @ $3.50) | I10: 0 | J10: 756 | K10: 756 | L10: C
A11: 202512-0071 | B11: 45994 | C11: 2025-12 | D11: Buffalo, NY | E11: Mid Atlantic | F11: Office & Admin Supplies | G11: Operating | H11: Office supplies | I11: 127.81 | J11: 0 | K11: 127.81 | L11: D
A12: 202512-0010 | B12: 45995 | C12: 2025-12 | D12: Boston, MA | E12: New England | F12: Sales Revenue - Espresso | G12: Revenue | H12: Daily POS sales batch - Espresso (272 cups @ $3.25) | I12: 0 | J12: 884 | K12: 884 | L12: C
A13: 202512-0056 | B13: 45995 | C13: 2025-12 | D13: Portland, ME | E13: New England | F13: Sales Revenue - Espresso | G13: Revenue | H13: Daily POS sales batch - Espresso (295 cups @ $3.25) | I13: 0 | J13: 958.75 | K13: 958.75 | L13: C
... A199: 202601-0098 | B199: 46051 | C199: 2026-01 | D199: Albany, NY | E199: Mid Atlantic | F199: Repairs & Maintenance | G199: Operating | H199: Repair & maintenance - door/hinge adjustment (work order #4697) | I199: 1264.37 | J199: 0 | K199: 1264.37 | L199: D

Sheet Expense analysis
A1: GL_Account | B1: Value for Dec 2025 | C1: Value for Jan 2026 | D1: % Change
A2: Bank & Card Processing Fees | B2: =SUMIFS(GL!$K:$K,GL!$F:$F,$A2,GL!$C:$C,"2025-12",GL!$L:$L,"D") -> 955.11 | C2: =SUMIFS(GL!$K:$K,GL!$F:$F,$A2,GL!$C:$C,"2026-01",GL!$L:$L,"D") -> 669.19 | D2: =IF($B2=0,"",($C2-$B2)/$B2) -> -0.29935819
A3: COGS - Coffee Beans | B3: =SUMIFS(GL!$K:$K,GL!$F:$F,$A3,GL!$C:$C,"2025-12",GL!$L:$L,"D") -> 1500 | C3: =SUMIFS(GL!$K:$K,GL!$F:$F,$A3,GL!$C:$C,"2026-01",GL!$L:$L,"D") -> 1637.56 | D3: =IF($B3=0,"",($C3-$B3)/$B3) -> 0.091706667
A4: COGS - Cups/Lids/Napkins | B4: =SUMIFS(GL!$K:$K,GL!$F:$F,$A4,GL!$C:$C,"2025-12",GL!$L:$L,"D") -> 938.6 | C4: =SUMIFS(GL!$K:$K,GL!$F:$F,$A4,GL!$C:$C,"2026-01",GL!$L:$L,"D") -> 674.55 | D4: =IF($B4=0,"",($C4-$B4)/$B4) -> -0.28132325
A5: COGS - Milk & Dairy | B5: =SUMIFS(GL!$K:$K,GL!$F:$F,$A5,GL!$C:$C,"2025-12",GL!$L:$L,"D") -> 2635.9 | C5: =SUMIFS(GL!$K:$K,GL!$F:$F,$A5,GL!$C:$C,"2026-01",GL!$L:$L,"D") -> 2198.06 | D5: =IF($B5=0,"",($C5-$B5)/$B5) -> -0.16610645
A6: Cleaning & Sanitation | B6: =SUMIFS(GL!$K:$K,GL!$F:$F,$A6,GL!$C:$C,"2025-12",GL!$L:$L,"D") -> 590 | C6: =SUMIFS(GL!$K:$K,GL!$F:$F,$A6,GL!$C:$C,"2026-01",GL!$L:$L,"D") -> 697.57 | D6: =IF($B6=0,"",($C6-$B6)/$B6) -> 0.18232203
A7: Delivery / Courier Fees | B7: =SUMIFS(GL!$K:$K,GL!$F:$F,$A7,GL!$C:$C,"2025-12",GL!$L:$L,"D") -> 400.41 | C7: =SUMIFS(GL!$K:$K,GL!$F:$F,$A7,GL!$C:$C,"2026-01",GL!$L:$L,"D") -> 393.22 | D7: =IF($B7=0,"",($C7-$B7)/$B7) -> -0.017956594
A8: Insurance Expense | B8: =SUMIFS(GL!$K:$K,GL!$F:$F,$A8,GL!$C:$C,"2025-12",GL!$L:$L,"D") -> 595.53 | C8: =SUMIFS(GL!$K:$K,GL!$F:$F,$A8,GL!$C:$C,"2026-01",GL!$L:$L,"D") -> 679.03 | D8: =IF($B8=0,"",($C8-$B8)/$B8) -> 0.14021124
A9: Marketing & Promotions | B9: =SUMIFS(GL!$K:$K,GL!$F:$F,$A9,GL!$C:$C,"2025-12",GL!$L:$L,"D") -> 1102.36 | C9: =SUMIFS(GL!$K:$K,GL!$F:$F,$A9,GL!$C:$C,"2026-01",GL!$L:$L,"D") -> 431.92 | D9: =IF($B9=0,"",($C9-$B9)/$B9) -> -0.60818607
A10: Office & Admin Supplies | B10: =SUMIFS(GL!$K:$K,GL!$F:$F,$A10,GL!$C:$C,"2025-12",GL!$L:$L,"D") -> 233.88 | C10: =SUMIFS(GL!$K:$K,GL!$F:$F,$A10,GL!$C:$C,"2026-01",GL!$L:$L,"D") -> 219.61 | D10: =IF($B10=0,"",($C10-$B10)/$B10) -> -0.061014195
A11: POS / Software Subscriptions | B11: =SUMIFS(GL!$K:$K,GL!$F:$F,$A11,GL!$C:$C,"2025-12",GL!$L:$L,"D") -> 586.45 | C11: =SUMIFS(GL!$K:$K,GL!$F:$F,$A11,GL!$C:$C,"2026-01",GL!$L:$L,"D") -> 373.58 | D11: =IF($B11=0,"",($C11-$B11)/$B11) -> -0.36298065
A12: Payroll Taxes | B12: =SUMIFS(GL!$K:$K,GL!$F:$F,$A12,GL!$C:$C,"2025-12",GL!$L:$L,"D") -> 1321.1 | C12: =SUMIFS(GL!$K:$K,GL!$F:$F,$A12,GL!$C:$C,"2026-01",GL!$L:$L,"D") -> 1026.88 | D12: =IF($B12=0,"",($C12-$B12)/$B12) -> -0.22270835
A13: Rent Expense | B13: =SUMIFS(GL!$K:$K,GL!$F:$F,$A13,GL!$C:$C,"2025-12",GL!$L:$L,"D") -> 5600 | C13: =SUMIFS(GL!$K:$K,GL!$F:$F,$A13,GL!$C:$C,"2026-01",GL!$L:$L,"D") -> 6336.66 | D13: =IF($B13=0,"",($C13-$B13)/$B13) -> 0.13154643
... A17: Wages - Baristas | B17: =SUMIFS(GL!$K:$K,GL!$F:$F,$A17,GL!$C:$C,"2025-12",GL!$L:$L,"D") -> 9064.57 | C17: =SUMIFS(GL!$K:$K,GL!$F:$F,$A17,GL!$C:$C,"2026-01",GL!$L:$L,"D") -> 7417.28 | D17: =IF($B17=0,"",($C17-$B17)/$B17) -> -0.18172842

Sheet Revenue analysis
A1: GL_Account | B1: Value for Dec 2025 | C1: Value for Jan 2026 | D1: % Change
A2: Sales Revenue - Cappuccino | B2: =SUMIFS(GL!$K:$K,GL!$F:$F,$A2,GL!$C:$C,"2025-12",GL!$L:$L,"C") -> 18742.5 | C2: =SUMIFS(GL!$K:$K,GL!$F:$F,$A2,GL!$C:$C,"2026-01",GL!$L:$L,"C") -> 14057.63 | D2: =IF($B2=0,"",($C2-$B2)/$B2) -> -0.24995972
A3: Sales Revenue - Espresso | B3: =SUMIFS(GL!$K:$K,GL!$F:$F,$A3,GL!$C:$C,"2025-12",GL!$L:$L,"C") -> 8014.5 | C3: =SUMIFS(GL!$K:$K,GL!$F:$F,$A3,GL!$C:$C,"2026-01",GL!$L:$L,"C") -> 11909 | D3: =IF($B3=0,"",($C3-$B3)/$B3) -> 0.48593175
A4: Sales Revenue - Mocha | B4: =SUMIFS(GL!$K:$K,GL!$F:$F,$A4,GL!$C:$C,"2025-12",GL!$L:$L,"C") -> 17329.35 | C4: =SUMIFS(GL!$K:$K,GL!$F:$F,$A4,GL!$C:$C,"2026-01",GL!$L:$L,"C") -> 18560.58 | D4: =IF($B4=0,"",($C4-$B4)/$B4) -> 0.071048828
