Workbook

Sheet Balance Sheet
A1: Assets | B1: 2024
A2: Current Assets
A3: Cash & Cash equivalents | B3: 125000
A4: Receivables | B4: 80000
A5: Prepaid expenses | B5: 25000
A6: Total Current Assets | B6: =SUM(B2:B5) -> 230000
A7: Non-current assets
A8: Equipment | B8: 95000
A9: Long-term investment | B9: 25000
A10: Intangible assets | B10: 120000
A11: Total Non-current assets | B11: =SUM(B7:B10) -> 240000
A12: TOTAL ASSETS | B12: =B11+B6 -> 470000
A13: Liabilities
A14: Current liabilities
A15: Accounts Payable | B15: 45000
A16: Income Tax Payable | B16: 40000
A17: Accrued Salaries | B17: 30000
A18: Unearned Revenue | B18: 45000
A19: Current Portion of Long-Term Debt | B19: 15000
A20: Total Current Liabilities | B20: =SUM(B15:B19) -> 175000
A21: Long-Term Debt | B21: 40000
A22: Other Long-Term Liabilities | B22: 15000
A23: Total Long-Term Liabilities | B23: =SUM(B21:B22) -> 55000
A24: TOTAL LIABILITIES | B24: =B23+B20 -> 230000
A25: Owner's Investment | B25: 100000
A26: Retained Earnings | B26: 140000
A27: TOTAL OWNER'S EQUITY | B27: =SUM(B25:B26) -> 240000
A29: TOTAL LIABILITIES & OWNER'S EQUITY | B29: =B27+B24 -> 470000

Sheet Profit Loss St.
A1: Category | B1: 2024
A2: Revenue
A3: Custom software development | B3: 600000
A4: Tech consultancy | B4: 200000
A5: IT suppport and services | B5: 28000
A6: Total Revenue | B6: =SUM(B3:B5) -> 828000
A8: Cost of Revenue
A9: Software Hosting & Maintenance Costs | B9: 50000
A10: Software Development Expenses | B10: 73000
A11: Consultant salaries | B11: 80000
A12: Total Cost of Revenue | B12: =SUM(B9:B11) -> 203000
A14: Gross Profit | B14: =B6-B12 -> 625000
A15: Operating Expenses
A16: Support staff salaries | B16: 80000
A17: Sales & Marketing | B17: 48000
A18: Customer Support & Maintenance | B18: 25000
A19: Depreciation & Amortization | B19: 32000
A20: Total Operating Expenses | B20: =SUM(B16:B19) -> 185000
A22: Operating Profit | B22: =B14-B20 -> 440000
A24: Interest & Other Expenses | B24: 48000
A25: Net Profit Before Tax | B25: =B22-B24 -> 392000
A27: Income Tax Expense | B27: 45000
A28: Net Profit After Tax | B28: =B25-B27 -> 347000

Sheet Ratios-Figure
A1: Accounting Ratio or Figure | B1: 2024
A2: Gross Profit Margin | B2: =('Profit Loss St.'!B6-'Profit Loss St.'!B12)/'Profit Loss St.'!B6 -> 0.75483092
A3: Operating Profit Margin (EBIT Margin) | B3: ='Profit Loss St.'!B22/'Profit Loss St.'!B6 -> 0.53140097
A4: Net Profit Margin | B4: ='Profit Loss St.'!B28/'Profit Loss St.'!B6 -> 0.41908213
A5: Current Ratio | B5: ='Balance Sheet'!B6/'Balance Sheet'!B20 -> 1.3142857
A6: Debt-to-Equity Ratio | B6: ='Balance Sheet'!B24/'Balance Sheet'!B27 -> 0.95833333
A7: Revenue Per Employee | B7: ='Profit Loss St.'!B6/B14 -> 33120
A8: Interest Coverage Ratio | B8: ='Profit Loss St.'!B22/'Profit Loss St.'!B24 -> 9.1666667
A9: Effective Tax Rate | B9: ='Profit Loss St.'!B27/'Profit Loss St.'!B25 -> 0.11479592
A11: Human Resource Ratios | B11: 2024
A12: Number of permanent employees | B12: 20
A13: Number of contractual employees-Consultants | B13: 5
A14: Total number of employees | B14: =B13+B12 -> 25
A16: Total Hiring Costs | B16: 25000
A17: Number of new hires | B17: 7
A19: Expected exchange rates | B19: Value
A20: Exchange rate (CAD/USD) | B20: 0.75
A21: Exchange rate (CAD/EUR) | B21: 0.65
A23: Revenue breakdown | B23: %
A24: Revenue from Europe | B24: 124200
A25: Revenue from America | B25: 331200
A26: Revenue from Canada | B26: 372600
A28: Market figures | B28: %
A29: Share of Canadian Market | B29: 2e-06
A30: Share of American Market | B30: 1e-06
A31: Share of European Market | B31: 1.8e-06
A32: Industry Growth Rate | B32: 0.02

Sheet Answer
A1: Priority | B1: Risk Title | C1: Recommended Metric | D1: Formula | E1: Calculation | F1: Proposed Responses
A2: 1 | B2: Currency Fluctuations (USD/CAD) | C2: Revenue at Risk (RaR) due to FX | D2: Foreign Revenue × Expected % Change in FX Rate | E2: =('Ratios-Figure'!B24*'Ratios-Figure'!B21)+('Ratios-Figure'!B25*'Ratios-Figure'!B20) -> 329130 | F2: Quantifies exposure to currency risk. In order to minimize the impact, Alpha Co. must expand local operations to mitigate the risk of currency fluctuations.
A3: 2 | B3: Competition & Market Saturation | C3: Market Share vs. Industry Growth Rate | D3: (European Market Share ÷ Industry growth rate)x100 | E3: =('Ratios-Figure'!B31/'Ratios-Figure'!B32)*100 -> 0.009 | F3: Having a small share in a market with steady growth indicates window of oppurtunity for Alpha Co. However, the competition is tough. Alpha Co. should improve its position by offering competitve services to its clients and offering new services to grow client base.
D4: (American Market Share ÷ Industry growth rate)x100 | E4: =('Ratios-Figure'!B30/'Ratios-Figure'!B32)*100 -> 0.005
A5: 3 | B5: Cross-Border Regulatory Changes | C5: Revenue Concentration by Region | D5: (European Revenue ÷ Total Revenue) * 100 | E5: =('Ratios-Figure'!B24/'Profit Loss St.'!B6)*100 -> 15 | F5: 40% concentration in American market asks for greater penetration in local market. This can be done through new product offering or attracting new clients.
D6: (American Revenue ÷Total Revenue) * 100 | E6: =('Ratios-Figure'!B25/'Profit Loss St.'!B6*100) -> 40
A7: 4 | B7: Key Personnel Dependency | C7: % Consultant Salary Cost | D7: Consultant Salaries ÷ Total Cost | E7: ='Profit Loss St.'!B11/'Profit Loss St.'!B12 -> 0.39408867 | F7: Indicates high dependency on consultants. The company can conduct training programs or review employment terms to reduce dependence on contracted employees.
