Workbook

Sheet Balance Sheet
A1: Assets | B1: 2024 | C1: 2023 | D1: 2022
A2: Current Assets
A3: Cash & Cash equivalents | B3: 65000 | C3: 55000 | D3: 40000
A4: Receivables | B4: 25000 | C4: 20000 | D4: 18000
A5: Prepaid expenses | B5: 5000 | C5: 4500 | D5: 3800
A6: Total Current Assets | B6: =SUM(B2:B5) -> 95000 | C6: =SUM(C2:C5) -> 79500 | D6: =SUM(D2:D5) -> 61800
A7: Non-current assets
A8: Equipment | B8: 15000 | C8: 12000 | D8: 10000
A9: Long-term investment | B9: 10000 | C9: 10000 | D9: 8000
A10: Intangible assets | B10: 650000 | C10: 600000 | D10: 500000
A11: Total Non-current assets | B11: =SUM(B7:B10) -> 675000 | C11: =SUM(C7:C10) -> 622000 | D11: =SUM(D7:D10) -> 518000
A12: TOTAL ASSETS | B12: =B11+B6 -> 770000 | C12: =C11+C6 -> 701500 | D12: =D11+D6 -> 579800
A13: Liabilities
A14: Current liabilities
A15: Accounts Payable | B15: 50000 | C15: 30000 | D15: 20000
A16: Income Tax Payable | B16: 40000 | C16: 25000 | D16: 20000
A17: Accrued Salaries | B17: 60000 | C17: 40000 | D17: 30000
A18: Unearned Revenue | B18: 50000 | C18: 30000 | D18: 20000
A19: Current Portion of Long-Term Debt | B19: 30000 | C19: 20000 | D19: 15000
A20: Total Current Liabilities | B20: =SUM(B15:B19) -> 230000 | C20: =SUM(C15:C19) -> 145000 | D20: =SUM(D15:D19) -> 105000
A21: Long-Term Debt | B21: 80000 | C21: 100000 | D21: 80000
A22: Other Long-Term Liabilities | B22: 40000 | C22: 30000 | D22: 20000
A23: Total Long-Term Liabilities | B23: =SUM(B21:B22) -> 120000 | C23: =SUM(C21:C22) -> 130000 | D23: =SUM(D21:D22) -> 100000
A24: TOTAL LIABILITIES | B24: =B23+B20 -> 350000 | C24: =C23+C20 -> 275000 | D24: =D23+D20 -> 205000
A25: Owner's Investment | B25: 22000 | C25: 210000 | D25: 200000
A26: Retained Earnings | B26: 398000 | C26: 26500 | D26: 24800
A27: TOTAL OWNER'S EQUITY | B27: =SUM(B25:B26) -> 420000 | C27: =SUM(C25:C26) -> 236500 | D27: =SUM(D25:D26) -> 224800
A29: TOTAL LIABILITIES & OWNER'S EQUITY | B29: =B27+B24 -> 770000 | C29: 701500 | D29: 579800

Sheet Profit Loss St.
A1: Category | B1: 2024 | C1: 2023 | D1: 2022
A2: Revenue
A3: Consulting services | B3: 500000 | C3: 400000 | D3: 350000
A4: Software Licensing | B4: 600000 | C4: 450000 | D4: 350000
A5: Training Services | B5: 230000 | C5: 120000 | D5: 0
A6: Total Revenue | B6: =SUM(B3:B5) -> 1330000 | C6: =SUM(C3:C5) -> 970000 | D6: =SUM(D3:D5) -> 700000 | F6: =500000/B6*100 -> 37.593985
A8: Cost of Revenue
A9: Software Hosting & Maintenance Costs | B9: 500000 | C9: 400000 | D9: 250000
A10: Software Development Expenses | B10: 80000 | C10: 50000 | D10: 40000
A11: Consultant salaries | B11: 35000 | C11: 25000 | D11: 18000
A12: Total Cost of Revenue | B12: =SUM(B9:B11) -> 615000 | C12: =SUM(C9:C11) -> 475000 | D12: =SUM(D9:D11) -> 308000
A14: Gross Profit | B14: =B6-B12 -> 715000 | C14: =C6-C12 -> 495000 | D14: =D6-D12 -> 392000
A15: Operating Expenses
A16: Support staff salaries | B16: 40000 | C16: 30000 | D16: 25000
A17: Sales & Marketing | B17: 60000 | C17: 30000 | D17: 20000
A18: Customer Support & Maintenance | B18: 19000 | C18: 13000 | D18: 10000
A19: Depreciation & Amortization | B19: 70000 | C19: 50000 | D19: 40000
A20: Total Operating Expenses | B20: =SUM(B16:B19) -> 189000 | C20: =SUM(C16:C19) -> 123000 | D20: =SUM(D16:D19) -> 95000
A22: Operating Profit | B22: =B14-B20 -> 526000 | C22: =C14-C20 -> 372000 | D22: =D14-D20 -> 297000
A24: Interest & Other Expenses | B24: 30000 | C24: 25000 | D24: 15000
A25: Net Profit Before Tax | B25: =B22-B24 -> 496000 | C25: =C22-C24 -> 347000 | D25: =D22-D24 -> 282000
A27: Income Tax Expense | B27: 30000 | C27: 28000 | D27: 15000
A28: Net Profit After Tax | B28: 800000 | C28: 560000 | D28: =D25-D27 -> 267000

Sheet Cashflow st.
A1: Category | B1: 2024 (USD) | C1: 2023 (USD) | D1: 2022 (USD)
A2: Cash Flow from Operating Activities
A3: Net Profit After Tax | B3: 800000 | C3: 560000 | D3: 267000
A4: Depreciation & Amortization | B4: 70000 | C4: 50000 | D4: 40000
A5: Changes in Accounts Receivable | B5: -5000 | C5: -2000 | D5: -1800
A6: Changes in Accounts Payable | B6: 20000 | C6: 10000 | D6: 8000
A7: Changes in Unearned Revenue | B7: 20000 | C7: 10000 | D7: 8000
A8: Net Cash from Operating Activities | B8: =SUM(B3:B7) -> 905000 | C8: =SUM(C3:C7) -> 628000 | D8: =SUM(D3:D7) -> 321200
A10: Cash Flow from Investing Activities
A11: Capitalized Software Development Costs | B11: -80000 | C11: -50000 | D11: -40000
A12: Purchase of Equipment | B12: -30000 | C12: -20000 | D12: -15000
A13: Net Cash from Investing Activities | B13: =B12+B11 -> -110000 | C13: =C12+C11 -> -70000 | D13: =D12+D11 -> -55000
A15: Cash Flow from Financing Activities
A16: Loan Proceeds | B16: 0 | C16: 0 | D16: 100000
A17: Loan Repayments | B17: -50000 | C17: -40000 | D17: -30000
A18: Equity Issuance | B18: 22000 | C18: 210000 | D18: 200000
A19: Dividend Payments | B19: -90000 | C19: -70000 | D19: -50000
A20: Net Cash from Financing Activities | B20: =SUM(B16:B19) -> -118000 | C20: =SUM(C16:C19) -> 100000 | D20: =SUM(D16:D19) -> 220000
A22: Net Increase in Cash | B22: 677000 | C22: 658000 | D22: 486200
A23: Beginning Cash Balance | B23: 55000 | C23: 40000 | D23: 20000
A24: Ending Cash Balance | B24: =B23+B22 -> 732000 | C24: =C23+C22 -> 698000 | D24: =D23+D22 -> 506200

Sheet Ratios
A1: Ratio or Figure | B1: 2024 | C1: 2023 | D1: 2022 | E1: Formula | F1: What does it measure | G1: Good Benchmark | H1: 2024 | I1: 2023 | J1: 2022
A2: Gross Profit Margin | B2: =('Profit Loss St.'!B6-'Profit Loss St.'!B12)/'Profit Loss St.'!B6 -> 0.53759398 | C2: =('Profit Loss St.'!C6-'Profit Loss St.'!C12)/'Profit Loss St.'!C6 -> 0.51030928 | D2: =('Profit Loss St.'!D6-'Profit Loss St.'!D12)/'Profit Loss St.'!D6 -> 0.56 | E2: (Revenue - Cost of Goods Sold) / Revenue | F2: Profitability before operating expenses | G2: 50% or higher | H2: =('Profit Loss St.'!B6-'Profit Loss St.'!B12)/'Profit Loss St.'!B6 -> 0.53759398 | I2: =('Profit Loss St.'!C6-'Profit Loss St.'!C12)/'Profit Loss St.'!C6 -> 0.51030928 | J2: =('Profit Loss St.'!D6-'Profit Loss St.'!D12)/'Profit Loss St.'!D6 -> 0.56
A3: Operating Profit Margin (EBIT Margin) | B3: ='Profit Loss St.'!B22/'Profit Loss St.'!B6 -> 0.39548872 | C3: ='Profit Loss St.'!C22/'Profit Loss St.'!C6 -> 0.38350515 | D3: ='Profit Loss St.'!D22/'Profit Loss St.'!D6 -> 0.42428571 | E3: Operating Income / Revenue | F3: Profitability after operating expenses but before interest and taxes | G3: 25% or higher | H3: ='Profit Loss St.'!B22/'Profit Loss St.'!B6 -> 0.39548872 | I3: ='Profit Loss St.'!C22/'Profit Loss St.'!C6 -> 0.38350515 | J3: ='Profit Loss St.'!D22/'Profit Loss St.'!D6 -> 0.42428571
A4: Net Profit Margin | B4: ='Profit Loss St.'!B28/'Profit Loss St.'!B6 -> 0.60150376 | C4: ='Profit Loss St.'!C28/'Profit Loss St.'!C6 -> 0.57731959 | D4: ='Profit Loss St.'!D28/'Profit Loss St.'!D6 -> 0.38142857 | E4: Net Income / Revenue | F4: Overall profitability after all expenses | G4: 15%-25% | H4: ='Profit Loss St.'!B28/'Profit Loss St.'!B6 -> 0.60150376 | I4: ='Profit Loss St.'!C28/'Profit Loss St.'!C6 -> 0.57731959 | J4: ='Profit Loss St.'!D28/'Profit Loss St.'!D6 -> 0.38142857
A5: Current Ratio | B5: ='Balance Sheet'!B6/'Balance Sheet'!B20 -> 0.41304348 | C5: ='Balance Sheet'!C6/'Balance Sheet'!C20 -> 0.54827586 | D5: ='Balance Sheet'!D6/'Balance Sheet'!D20 -> 0.58857143 | E5: Current Assets / Current Liabilities | F5: Liquidity and ability to cover short-term liabilities | G5: 1.5 to 2.0 | H5: ='Balance Sheet'!B6/'Balance Sheet'!B20 -> 0.41304348 | I5: ='Balance Sheet'!C6/'Balance Sheet'!C20 -> 0.54827586 | J5: ='Balance Sheet'!D6/'Balance Sheet'!D20 -> 0.58857143
A6: Debt-to-Equity Ratio | B6: ='Balance Sheet'!B24/'Balance Sheet'!B27 -> 0.83333333 | C6: ='Balance Sheet'!C24/'Balance Sheet'!C27 -> 1.1627907 | D6: ='Balance Sheet'!D24/'Balance Sheet'!D27 -> 0.91192171 | E6: Total Debt / Total Equity | F6: Financial leverage and capital structure | G6: Below 1.0 | H6: ='Balance Sheet'!B24/'Balance Sheet'!B27 -> 0.83333333 | I6: ='Balance Sheet'!C24/'Balance Sheet'!C27 -> 1.1627907 | J6: ='Balance Sheet'!D24/'Balance Sheet'!D27 -> 0.91192171
A7: Revenue Per Employee | B7: ='Profit Loss St.'!B6/15 -> 88666.667 | C7: ='Profit Loss St.'!C6/15 -> 64666.667 | D7: ='Profit Loss St.'!D6/15 -> 46666.667 | E7: Total Revenue / Number of Employees | F7: Productivity and efficiency of workforce | G7: Varies by industry | H7: ='Profit Loss St.'!B6/15 -> 88666.667 | I7: ='Profit Loss St.'!C6/15 -> 64666.667 | J7: ='Profit Loss St.'!D6/15 -> 46666.667
A8: Interest Coverage Ratio | B8: ='Profit Loss St.'!B22/'Profit Loss St.'!B24 -> 17.533333 | C8: ='Profit Loss St.'!C22/'Profit Loss St.'!C24 -> 14.88 | D8: ='Profit Loss St.'!D22/'Profit Loss St.'!D24 -> 19.8 | E8: EBIT / Interest Expense | F8: Ability to cover interest payments | G8: 3.0 or higher | H8: ='Profit Loss St.'!B22/'Profit Loss St.'!B24 -> 17.533333 | I8: ='Profit Loss St.'!C22/'Profit Loss St.'!C24 -> 14.88 | J8: ='Profit Loss St.'!D22/'Profit Loss St.'!D24 -> 19.8
A9: Effective Tax Rate | B9: ='Profit Loss St.'!B27/'Profit Loss St.'!B25 -> 0.060483871 | C9: ='Profit Loss St.'!C27/'Profit Loss St.'!C25 -> 0.080691643 | D9: ='Profit Loss St.'!D27/'Profit Loss St.'!D25 -> 0.053191489 | E9: Tax Expense / Earnings Before Tax | F9: Percentage of earnings paid as tax | G9: Varies by jurisdiction | H9: ='Profit Loss St.'!B27/'Profit Loss St.'!B25 -> 0.060483871 | I9: ='Profit Loss St.'!C27/'Profit Loss St.'!C25 -> 0.080691643 | J9: ='Profit Loss St.'!D27/'Profit Loss St.'!D25 -> 0.053191489
