Workbook
Name Base_Cappuccino_MidAtlantic: Drivers!$B$9:$E$9
Name Base_Cappuccino_NewEngland: Drivers!$B$6:$E$6
Name Base_Espresso_MidAtlantic: Drivers!$B$10:$E$10
Name Base_Espresso_NewEngland: Drivers!$B$7:$E$7
Name Base_Mocha_MidAtlantic: Drivers!$B$11:$E$11
Name Base_Mocha_NewEngland: Drivers!$B$8:$E$8
Name Cappuccino_Price: Drivers!$B$1
Name case_product_region: Drivers!$B$6:$E$23
Name daily_volume: Drivers!$B$6:$E$23
Name Daily_volume_dec_25: Drivers!$D$6:$D$23
Name Daily_volume_nov_25: Drivers!$C$6:$C$23
Name Daily_volume_oct_25: Drivers!$B$6:$B$23
Name daily_volume_Q4: Drivers!$E$6:$E$23
Name Dec_25: Drivers!$D$6:$D$23
Name Downside_Cappuccino_MidAtlantic: Drivers!$B$21:$E$21
Name Downside_Cappuccino_NewEngland: Drivers!$B$18:$E$18
Name Downside_Espresso_MidAtlantic: Drivers!$B$22:$E$22
Name Downside_Espresso_NewEngland: Drivers!$B$19:$E$19
Name Downside_Mocha_MidAtlantic: Drivers!$B$23:$E$23
Name Downside_Mocha_NewEngland: Drivers!$B$20:$E$20
Name Espresso_Price: Drivers!$B$2
Name Mocha_Price: Drivers!$B$3
Name Nov_25: Drivers!$C$6:$C$23
Name Oct_25: Drivers!$B$6:$B$23
Name Q4_Total: Drivers!$E$6:$E$23
Name Upside_Cappuccino_MidAtlantic: Drivers!$B$15:$E$15
Name Upside_Cappuccino_NewEngland: Drivers!$B$12:$E$12
Name Upside_Espresso_MidAtlantic: Drivers!$B$16:$E$16
Name Upside_Espresso_NewEngland: Drivers!$B$13:$E$13
Name Upside_Mocha_MidAtlantic: Drivers!$B$17:$E$17
Name Upside_Mocha_NewEngland: Drivers!$B$14:$E$14

Sheet Calculations
A2: Scenario Selector | B2: Upside
A4: Product | B4: Q4 2025 Total Volume New England | C4: Gross Revenue New England | D4: Q4 2025 Total Volume Mid Atlantic | E4: Gross Revenue Mid Atlantic | F4: Q4 2025 Total Gross Revenue
A5: Cappuccino | B5: =INDEX(Drivers!$E$6:$E$23, MATCH(PROPER($B$2)&"_"&$A5&"_NewEngland", Drivers!$A$6:$A$23, 0)) -> 91 | C5: =B5*Cappuccino_Price -> 318.5 | D5: =INDEX(Drivers!$E$6:$E$23, MATCH(PROPER($B$2)&"_"&$A5&"_MidAtlantic", Drivers!$A$6:$A$23, 0)) -> 107 | E5: =D5*Cappuccino_Price -> 374.5 | F5: =E5+C5 -> 693
A6: Espresso | B6: =INDEX(Drivers!$E$6:$E$23, MATCH(PROPER($B$2)&"_"&$A6&"_NewEngland", Drivers!$A$6:$A$23, 0)) -> 60 | C6: =B6*Espresso_Price -> 195 | D6: =INDEX(Drivers!$E$6:$E$23, MATCH(PROPER($B$2)&"_"&$A6&"_MidAtlantic", Drivers!$A$6:$A$23, 0)) -> 98 | E6: =D6*Espresso_Price -> 318.5 | F6: =E6+C6 -> 513.5
A7: Mocha | B7: =INDEX(Drivers!$E$6:$E$23, MATCH(PROPER($B$2)&"_"&$A7&"_NewEngland", Drivers!$A$6:$A$23, 0)) -> 72 | C7: =B7*Mocha_Price -> 248.4 | D7: =INDEX(Drivers!$E$6:$E$23, MATCH(PROPER($B$2)&"_"&$A7&"_MidAtlantic", Drivers!$A$6:$A$23, 0)) -> 88 | E7: =D7*Mocha_Price -> 303.6 | F7: =E7+C7 -> 552
A8: Total | B8: =SUM(B5:B7) -> 223 | C8: =SUM(C5:C7) -> 761.9 | D8: =SUM(D5:D7) -> 293 | E8: =SUM(E5:E7) -> 996.6 | F8: =SUM(F5:F7) -> 1758.5

Sheet Drivers
A1: Cappuccino Price | B1: 3.5
A2: Espresso Price | B2: 3.25
A3: Mocha Price | B3: 3.45
A5: daily_volume | B5: Daily_volume_oct_25 | C5: Daily_volume_nov_25 | D5: Daily_volume_dec_25 | E5: Q4_total_volume
A6: Base_Cappuccino_NewEngland | B6: 27 | C6: 19 | D6: 20 | E6: =SUM(B6:D6) -> 66
A7: Base_Espresso_NewEngland | B7: 11 | C7: 16 | D7: 14 | E7: =SUM(B7:D7) -> 41
A8: Base_Mocha_NewEngland | B8: 14 | C8: 23 | D8: 19 | E8: =SUM(B8:D8) -> 56
A9: Base_Cappuccino_MidAtlantic | B9: 28 | C9: 36 | D9: 34 | E9: =SUM(B9:D9) -> 98
A10: Base_Espresso_MidAtlantic | B10: 27 | C10: 35 | D10: 25 | E10: =SUM(B10:D10) -> 87
A11: Base_Mocha_MidAtlantic | B11: 21 | C11: 26 | D11: 22 | E11: =SUM(B11:D11) -> 69
A12: Upside_Cappuccino_NewEngland | B12: 38 | C12: 28 | D12: 25 | E12: =SUM(B12:D12) -> 91
A13: Upside_Espresso_NewEngland | B13: 18 | C13: 22 | D13: 20 | E13: =SUM(B13:D13) -> 60
A14: Upside_Mocha_NewEngland | B14: 19 | C14: 28 | D14: 25 | E14: =SUM(B14:D14) -> 72
A15: Upside_Cappuccino_MidAtlantic | B15: 35 | C15: 42 | D15: 30 | E15: =SUM(B15:D15) -> 107
A16: Upside_Espresso_MidAtlantic | B16: 30 | C16: 39 | D16: 29 | E16: =SUM(B16:D16) -> 98
A17: Upside_Mocha_MidAtlantic | B17: 25 | C17: 35 | D17: 28 | E17: =SUM(B17:D17) -> 88
... A23: Downside_Mocha_MidAtlantic | B23: 18 | C23: 23 | D23: 20 | E23: =SUM(B23:D23) -> 61
A25: Sales Tax | B25: 0.12
A26: Business Tax | B26: 0.15
